LICENSE.txt
MANIFEST.in
README.md
ez_setup.py
setup.py
apode/__init__.py
apode/basic.py
apode/concentration.py
apode/datasets.py
apode/inequality.py
apode/plots.py
apode/polarization.py
apode/poverty.py
apode/welfare.py
apode.egg-info/PKG-INFO
apode.egg-info/SOURCES.txt
apode.egg-info/dependency_links.txt
apode.egg-info/requires.txt
apode.egg-info/top_level.txt
res/logo.png