Metadata-Version: 2.1
Name: apode
Version: 0.1.0
Summary: Poverty and Inequality Analysis in Python
Home-page: https://github.com/ngrion/apode
Author: ['Néstor Grión', 'Sofia Sappia']
Author-email: ngrion@gmail.com
License: MIT
Keywords: apode,poverty,inequality,concentration,welfare,polarization
Platform: UNKNOWN
Classifier: Development Status :: 4 - Beta
Classifier: Intended Audience :: Education
Classifier: Intended Audience :: Science/Research
Classifier: License :: OSI Approved :: MIT License
Classifier: Operating System :: OS Independent
Classifier: Programming Language :: Python
Classifier: Programming Language :: Python :: 3.8
Classifier: Programming Language :: Python :: Implementation :: CPython
Classifier: Topic :: Scientific/Engineering
